Metadata-Version: 2.1
Name: mercurio
Version: 0.10.2
Summary: Send email with python, my way
Home-page: https://github.com/pietrogiuffrida/mercurio/
Author: Pietro Giuffrida
Author-email: pietro.giuffri@gmail.com
License: MIT
Platform: UNKNOWN
Classifier: Programming Language :: Python :: 3
Classifier: License :: OSI Approved :: MIT License
Classifier: Operating System :: OS Independent
